appdomain/__init__.py
appdomain/base.py
appdomain/classisolation.py
appdomain/ensemble.py
appdomain/knn.py
appdomain-0.1.2.dist-info/METADATA
appdomain-0.1.2.dist-info/WHEEL
appdomain-0.1.2.dist-info/top_level.txt
appdomain-0.1.2.dist-info/RECORD
